xl2roefact-0.8.dist-info/METADATA
xl2roefact-0.8.dist-info/WHEEL
xl2roefact-0.8.dist-info/entry_points.txt
xl2roefact-0.8.dist-info/licenses/LICENSE
xl2roefact/__init__.py
xl2roefact/__main__.py
xl2roefact/__version__.py
xl2roefact/app_cli.py
xl2roefact/chkisld.py
xl2roefact/chkxml.py
xl2roefact/config_settings.py
xl2roefact/data/README_app_config_rules.md
xl2roefact/data/__init__.py
xl2roefact/data/app_settings.yml
xl2roefact/ldxml.py
xl2roefact/libutils.py
xl2roefact/rdinv.py
xl2roefact/sys_settings.py
xl2roefact/wrxml.py
xl2roefact-0.8.dist-info/RECORD
