Metadata-Version: 2.1
Name: xl2roefact
Version: 0.8
Summary: Excel invoices data retrieve, export & upload to RO E-Fact system
Author-Email: Petre Iordanescu <petre.iordanescu@gmail.com>, RENware Software Systems <renware.systems@gmail.com>
License:                     GNU GENERAL PUBLIC LICENSE
Classifier: Programming Language :: Python :: 3.10
Classifier: Programming Language :: Python :: 3.11
Classifier: Development Status :: 4 - Beta
Classifier: Intended Audience :: End Users/Desktop
Classifier: License :: OSI Approved :: GNU General Public License (GPL)
Classifier: Operating System :: OS Independent
Classifier: Topic :: Office/Business :: Financial
Project-URL: Homepage, https://invoicetoroefact.renware.eu
Project-URL: Pdf-documentation, https://invoicetoroefact.renware.eu/pdfs/print_page.html/print_page.pdf
Project-URL: Pypi-package, https://pypi.org/project/xl2roefact/
Project-URL: Github, https://github.com/petre-renware/api_to_roefact
Requires-Python: <3.12,>=3.9
Requires-Dist: altgraph~=0.17
Requires-Dist: argcomplete~=3.2
Requires-Dist: commonmark~=0.9
Requires-Dist: et-xmlfile~=1.1
Requires-Dist: Fraction~=2.2
Requires-Dist: Jinja2~=3.1
Requires-Dist: lief~=0.13
Requires-Dist: markdown-it-py~=3.0
Requires-Dist: MarkupSafe~=2.1
Requires-Dist: mdurl~=0.1
Requires-Dist: openpyxl~=3.1
Requires-Dist: packaging~=23.2
Requires-Dist: pefile~=2023.2
Requires-Dist: pdm~=2.12
Requires-Dist: pip~=24.0
Requires-Dist: platformdirs~=4.1
Requires-Dist: Pygments~=2.17
Requires-Dist: pylightxl~=1.61
Requires-Dist: pyproject-hooks~=1.0
Requires-Dist: python-dateutil~=2.8
Requires-Dist: pytzdata~=2020.1
Requires-Dist: pywin32-ctypes~=0.2
Requires-Dist: rich~=13.7
Requires-Dist: setuptools~=69.0
Requires-Dist: shellingham~=1.5
Requires-Dist: six~=1.16
Requires-Dist: time-machine~=2.13
Requires-Dist: tomli~=2.0
Requires-Dist: click~=8.1
Requires-Dist: typer~=0.9
Requires-Dist: typing-extensions~=4.9
Requires-Dist: tzdata~=2023.4
Requires-Dist: userpath~=1.9
Requires-Dist: wheel~=0.42
Requires-Dist: msgpack>=1.0.8
Requires-Dist: pyyaml>=6.0.1
